sumo/__init__.py
sumo/cli/__init__.py
sumo/cli/bandplot.py
sumo/cli/bandstats.py
sumo/cli/dosplot.py
sumo/cli/kgen.py
sumo/cli/optplot.py
sumo/cli/phonon_bandplot.py
sumo/electronic_structure/__init__.py
sumo/electronic_structure/bandstructure.py
sumo/electronic_structure/dos.py
sumo/electronic_structure/effective_mass.py
sumo/electronic_structure/optics.py
sumo/io/__init__.py
sumo/io/castep.py
sumo/io/questaal.py
sumo/io/vasp.py
sumo/phonon/__init__.py
sumo/phonon/phonopy.py
sumo/plotting/__init__.py
sumo/plotting/bs_plotter.py
sumo/plotting/dos_plotter.py
sumo/plotting/optics_plotter.py
sumo/plotting/orbital_colours.conf
sumo/plotting/phonon_bs_plotter.py
sumo/plotting/sumo_base.mplstyle
sumo/plotting/sumo_bs.mplstyle
sumo/plotting/sumo_dos.mplstyle
sumo/plotting/sumo_optics.mplstyle
sumo/plotting/sumo_phonon.mplstyle
sumo/symmetry/__init__.py
sumo/symmetry/brad_crack_kpath.py
sumo/symmetry/bradcrack.json
sumo/symmetry/custom_kpath.py
sumo/symmetry/kpath.py
sumo/symmetry/kpoints.py
sumo/symmetry/latimer_munro_kpath.py
sumo/symmetry/pymatgen_kpath.py
sumo/symmetry/seekpath_kpath.py
sumo-2.3.12.data/data/LICENSE
sumo-2.3.12.data/data/orbital_colours.conf
tests/tests_electronic_structure/__init__.py
tests/tests_electronic_structure/test_dos.py
tests/tests_electronic_structure/test_optics.py
tests/tests_io/__init__.py
tests/tests_io/test_castep.py
tests/tests_io/test_questaal.py
tests/tests_phonon/__init__.py
tests/tests_phonon/test_phonopy.py
tests/tests_plotting/__init__.py
tests/tests_plotting/test_band_plotter.py
tests/tests_plotting/test_dos_plotter.py
tests/tests_symmetry/__init__.py
tests/tests_symmetry/test_bradcrack_kpath.py
tests/tests_symmetry/test_custom_kpath.py
tests/tests_symmetry/test_pymatgen_kpath.py
tests/tests_symmetry/test_seekpath_kpath.py
sumo-2.3.12.dist-info/LICENSE
sumo-2.3.12.dist-info/METADATA
sumo-2.3.12.dist-info/WHEEL
sumo-2.3.12.dist-info/entry_points.txt
sumo-2.3.12.dist-info/top_level.txt
sumo-2.3.12.dist-info/RECORD
